{
  "effects": [
    {
      "effect": "overworld",
      "weight": 32
    },
    {
      "effect": "the_end",
      "weight": 8
    },
    {
      "effect": "multiverse:fog/white"
    },
    {
      "effect": "multiverse:fog/orange"
    },
    {
      "effect": "multiverse:fog/magenta"
    },
    {
      "effect": "multiverse:fog/light_blue"
    },
    {
      "effect": "multiverse:fog/yellow"
    },
    {
      "effect": "multiverse:fog/lime"
    },
    {
      "effect": "multiverse:fog/pink"
    },
    {
      "effect": "multiverse:fog/gray"
    },
    {
      "effect": "multiverse:fog/light_gray"
    },
    {
      "effect": "multiverse:fog/cyan"
    },
    {
      "effect": "multiverse:fog/purple"
    },
    {
      "effect": "multiverse:fog/blue"
    },
    {
      "effect": "multiverse:fog/brown"
    },
    {
      "effect": "multiverse:fog/green"
    },
    {
      "effect": "multiverse:fog/red"
    },
    {
      "effect": "multiverse:fog/black"
    }
  ]
}

